{
 "cells": [
  {
   "cell_type": "markdown",
   "metadata": {},
   "source": [
    "# EXAMPLES LEC 07 PYTHON MODULS"
   ]
  },
  {
   "cell_type": "markdown",
   "metadata": {},
   "source": [
    "### ФУНКЦИЯ"
   ]
  },
  {
   "cell_type": "code",
   "execution_count": 6,
   "metadata": {},
   "outputs": [
    {
     "name": "stdout",
     "output_type": "stream",
     "text": [
      "36\n"
     ]
    }
   ],
   "source": [
    "def foo(x,y):\n",
    "    X = 5\n",
    "    Y = 7\n",
    "    Z = X * Y\n",
    "    rer = x+Z\n",
    "    print(rer)\n",
    "    \n",
    "foo(1,2)    "
   ]
  },
  {
   "cell_type": "code",
   "execution_count": 7,
   "metadata": {},
   "outputs": [
    {
     "data": {
      "text/plain": [
       "<function __main__.foo(x, y)>"
      ]
     },
     "execution_count": 7,
     "metadata": {},
     "output_type": "execute_result"
    }
   ],
   "source": [
    "foo"
   ]
  },
  {
   "cell_type": "code",
   "execution_count": 8,
   "metadata": {},
   "outputs": [
    {
     "data": {
      "text/plain": [
       "2"
      ]
     },
     "execution_count": 8,
     "metadata": {},
     "output_type": "execute_result"
    }
   ],
   "source": [
    "#dir(foo.__code__)\n",
    "foo.__code__.co_argcount"
   ]
  },
  {
   "cell_type": "markdown",
   "metadata": {},
   "source": [
    "## ИМЕНА ПЕРЕМЕННЫХ"
   ]
  },
  {
   "cell_type": "code",
   "execution_count": 9,
   "metadata": {},
   "outputs": [
    {
     "data": {
      "text/plain": [
       "('x', 'y', 'X', 'Y', 'Z', 'rer')"
      ]
     },
     "execution_count": 9,
     "metadata": {},
     "output_type": "execute_result"
    }
   ],
   "source": [
    "foo.__code__.co_varnames"
   ]
  },
  {
   "cell_type": "markdown",
   "metadata": {},
   "source": [
    "## БАЙТ КОД "
   ]
  },
  {
   "cell_type": "code",
   "execution_count": 10,
   "metadata": {},
   "outputs": [
    {
     "data": {
      "text/plain": [
       "b'd\\x01}\\x02d\\x02}\\x03|\\x02|\\x03\\x14\\x00}\\x04|\\x00|\\x04\\x17\\x00}\\x05t\\x00|\\x05\\x83\\x01\\x01\\x00d\\x00S\\x00'"
      ]
     },
     "execution_count": 10,
     "metadata": {},
     "output_type": "execute_result"
    }
   ],
   "source": [
    "foo.__code__.co_code"
   ]
  },
  {
   "cell_type": "markdown",
   "metadata": {},
   "source": [
    "## БАЙТ КОД МНЕМОНИЧЕСКИЙ"
   ]
  },
  {
   "cell_type": "code",
   "execution_count": 11,
   "metadata": {},
   "outputs": [
    {
     "name": "stdout",
     "output_type": "stream",
     "text": [
      "  2           0 LOAD_CONST               1 (5)\n",
      "              2 STORE_FAST               2 (X)\n",
      "\n",
      "  3           4 LOAD_CONST               2 (7)\n",
      "              6 STORE_FAST               3 (Y)\n",
      "\n",
      "  4           8 LOAD_FAST                2 (X)\n",
      "             10 LOAD_FAST                3 (Y)\n",
      "             12 BINARY_MULTIPLY\n",
      "             14 STORE_FAST               4 (Z)\n",
      "\n",
      "  5          16 LOAD_FAST                0 (x)\n",
      "             18 LOAD_FAST                4 (Z)\n",
      "             20 BINARY_ADD\n",
      "             22 STORE_FAST               5 (rer)\n",
      "\n",
      "  6          24 LOAD_GLOBAL              0 (print)\n",
      "             26 LOAD_FAST                5 (rer)\n",
      "             28 CALL_FUNCTION            1\n",
      "             30 POP_TOP\n",
      "             32 LOAD_CONST               0 (None)\n",
      "             34 RETURN_VALUE\n"
     ]
    }
   ],
   "source": [
    "import dis\n",
    "dis.dis(foo.__code__)"
   ]
  },
  {
   "cell_type": "markdown",
   "metadata": {},
   "source": [
    "# ИМПОРТ МОДУЛЯ"
   ]
  },
  {
   "cell_type": "code",
   "execution_count": null,
   "metadata": {},
   "outputs": [],
   "source": [
    "import math"
   ]
  },
  {
   "cell_type": "code",
   "execution_count": null,
   "metadata": {},
   "outputs": [],
   "source": [
    "math"
   ]
  },
  {
   "cell_type": "code",
   "execution_count": null,
   "metadata": {},
   "outputs": [],
   "source": [
    "dir(math)"
   ]
  },
  {
   "cell_type": "code",
   "execution_count": null,
   "metadata": {},
   "outputs": [],
   "source": [
    "math.__doc__"
   ]
  },
  {
   "cell_type": "code",
   "execution_count": null,
   "metadata": {},
   "outputs": [],
   "source": [
    "pow(2,2)"
   ]
  },
  {
   "cell_type": "code",
   "execution_count": null,
   "metadata": {},
   "outputs": [],
   "source": [
    "math.pow(2,2)"
   ]
  },
  {
   "cell_type": "code",
   "execution_count": null,
   "metadata": {},
   "outputs": [],
   "source": [
    "help(math.pow)"
   ]
  },
  {
   "cell_type": "code",
   "execution_count": null,
   "metadata": {},
   "outputs": [],
   "source": []
  }
 ],
 "metadata": {
  "kernelspec": {
   "display_name": "Python 3",
   "language": "python",
   "name": "python3"
  },
  "language_info": {
   "codemirror_mode": {
    "name": "ipython",
    "version": 3
   },
   "file_extension": ".py",
   "mimetype": "text/x-python",
   "name": "python",
   "nbconvert_exporter": "python",
   "pygments_lexer": "ipython3",
   "version": "3.8.5"
  }
 },
 "nbformat": 4,
 "nbformat_minor": 4
}
